[
	{
		"time": 1771628670277,
		"file": "2026-02-20-23-04-30.zip",
		"index": 86,
		"success": true,
		"size": 182836906
	},
	{
		"time": 1771630470335,
		"file": "2026-02-20-23-34-30.zip",
		"index": 87,
		"success": true,
		"size": 182834883
	},
	{
		"time": 1771632270376,
		"file": "2026-02-21-00-04-30.zip",
		"index": 88,
		"success": true,
		"size": 182836636
	},
	{
		"time": 1771634070376,
		"file": "2026-02-21-00-34-30.zip",
		"index": 89,
		"success": true,
		"size": 182839815
	},
	{
		"time": 1771635870438,
		"file": "2026-02-21-01-04-30.zip",
		"index": 90,
		"success": true,
		"size": 182840206
	}
]